LICENSE
README.md
setup.cfg
setup.py
multicraft/__init__.py
multicraft/hosts.py
multicraft/model.py
multicraft.egg-info/PKG-INFO
multicraft.egg-info/SOURCES.txt
multicraft.egg-info/dependency_links.txt
multicraft.egg-info/requires.txt
multicraft.egg-info/top_level.txt