Metadata-Version: 2.1
Name: multicraft
Version: 0.0.1
Summary: Interact with your Minecraft server from hosts that use Multicraft using Python
Home-page: https://github.com/legopitstop/multicraft-py
Author: Legopitstop
Author-email: officiallegopitstop@gmail.com
License: MIT
Keywords: multicraft,minecraft,minecraftserver,server
Classifier: Development Status :: 4 - Beta
Classifier: Intended Audience :: Developers
Classifier: Topic :: Software Development :: Build Tools
Classifier: License :: OSI Approved :: MIT License
Classifier: Operating System :: Microsoft :: Windows
Classifier: Programming Language :: Python :: 3.11
Requires-Python: >=3.10
License-File: LICENSE
